moticon_opengo/__about__.py
moticon_opengo/__init__.py
moticon_opengo/gait_report.py
moticon_opengo/txt_export.py
moticon_opengo/utils.py
moticon_opengo-1.0.3.dist-info/METADATA
moticon_opengo-1.0.3.dist-info/WHEEL
moticon_opengo-1.0.3.dist-info/licenses/LICENSE
moticon_opengo-1.0.3.dist-info/RECORD
