Metadata-Version: 2.3
Name: moticon_opengo
Version: 1.0.3
Summary: Moticon OpenGo Library
Project-URL: Homepage, https://github.com/moticon-rego/moticon-opengo
Project-URL: Bug Tracker, https://github.com/moticon-rego/moticon-opengo/issues
Author-email: Moticon ReGo AG <support@moticon.com>
License:                                  Apache License
License-File: LICENSE
Classifier: License :: OSI Approved :: Apache Software License
Classifier: Operating System :: OS Independent
Classifier: Programming Language :: Python :: 3
Requires-Python: >=3.7
Requires-Dist: matplotlib
Requires-Dist: numpy
Requires-Dist: openpyxl
Provides-Extra: dev
Requires-Dist: ruff; extra == 'dev'
Provides-Extra: test
Requires-Dist: pytest; extra == 'test'
